{
  "metrics": {
    "us_10y_yield": {
      "value": 4.19,
      "delta": 0.0
    },
    "fed_net_liquidity": {
      "value": 6573.6,
      "delta": -1.009212995172138
    },
    "btc_price": {
      "value": 90628,
      "delta": -3.308474431606013
    },
    "stablecoin_mcap": {
      "value": 306.94,
      "delta": -0.21708589081311258
    },
    "usdt_dominance": {
      "value": 5.87,
      "delta": 3.311169256630062
    },
    "rwa_tvl": {
      "value": 8.5,
      "delta": 0.0
    }
  },
  "global_risk_status": "Risk Off",
  "btc_funding_rate": {
    "value": 0,
    "source": "error"
  },
  "btc_etf_flows": {
    "flows": [
      {
        "date": "2026-01-05",
        "flow": 150
      },
      {
        "date": "2026-01-06",
        "flow": -50
      },
      {
        "date": "2026-01-07",
        "flow": 300
      },
      {
        "date": "2026-01-08",
        "flow": 100
      },
      {
        "date": "2026-01-09",
        "flow": 200
      }
    ],
    "net_5day": 0.7
  },
  "correlation_radar": {
    "btc_nasdaq": 0.82,
    "btc_gold": -0.08,
    "interpretation": "Macro Driven",
    "period_days": 30
  },
  "polymarket_top5": [
    {
      "title": "Will tariffs generate >$250b in 2025?",
      "outcome": "No 99%",
      "probability": 0.987,
      "volume": 1037578.324818,
      "volume_24h": 0,
      "flipped": false,
      "url": "https://polymarket.com/event/will-tariffs-generate-250b-in-2025"
    },
    {
      "title": "Will the U.S. collect between $100b and $200b in revenue in 2025?",
      "outcome": "No 70%",
      "probability": 0.7,
      "volume": 759354.480673,
      "volume_24h": 0,
      "flipped": false,
      "url": "https://polymarket.com/event/will-the-us-collect-between-100b-and-200b-in-revenue-in-2025"
    },
    {
      "title": "Will Elon and DOGE cut more than $250b in federal spending in 2025?",
      "outcome": "No 99%",
      "probability": 0.994,
      "volume": 660211.924576,
      "volume_24h": 0,
      "flipped": false,
      "url": "https://polymarket.com/event/will-elon-and-doge-cut-more-than-250b-in-federal-spending-in-2025"
    },
    {
      "title": "Will the U.S. collect less than $100b in revenue in 2025?",
      "outcome": "No 72%",
      "probability": 0.7185,
      "volume": 658810.793328,
      "volume_24h": 0,
      "flipped": false,
      "url": "https://polymarket.com/event/will-the-us-collect-less-than-100b-in-revenue-in-2025"
    },
    {
      "title": "Will Elon and DOGE cut between $200-250b in federal spending in 2025?",
      "outcome": "No 100%",
      "probability": 0.9995,
      "volume": 417553.503307,
      "volume_24h": 0,
      "flipped": false,
      "url": "https://polymarket.com/event/will-elon-and-doge-cut-between-200-250b-in-federal-spending-in-2025"
    }
  ],
  "last_updated": "2026-01-10T10:15:46.282517Z"
}